submitr/__init__.py
submitr/base.py
submitr/config/custom_column_mappings.json
submitr/exceptions.py
submitr/file_for_upload.py
submitr/metadata_template.py
submitr/output.py
submitr/rclone/__init__.py
submitr/rclone/amazon_credentials.py
submitr/rclone/google_credentials.py
submitr/rclone/rclone_amazon.py
submitr/rclone/rclone_commands.py
submitr/rclone/rclone_google.py
submitr/rclone/rclone_installation.py
submitr/rclone/rclone_store.py
submitr/rclone/rclone_store_registry.py
submitr/rclone/rclone_utils.py
submitr/rclone/rcloner.py
submitr/rclone/testing/rclone_utils_for_testing_amazon.py
submitr/rclone/testing/rclone_utils_for_testing_google.py
submitr/s3_upload.py
submitr/s3_utils.py
submitr/scripts/__init__.py
submitr/scripts/check_submission.py
submitr/scripts/cli_utils.py
submitr/scripts/get_metadata_template.py
submitr/scripts/list_submissions.py
submitr/scripts/make_sample_fastq_file.py
submitr/scripts/rcloner.py
submitr/scripts/resume_uploads.py
submitr/scripts/show_upload_info.py
submitr/scripts/submit_genelist.py
submitr/scripts/submit_metadata_bundle.py
submitr/scripts/submit_ontology.py
submitr/scripts/submitr.py
submitr/scripts/upload_item_data.py
submitr/submission.py
submitr/submission_uploads.py
submitr/tests/__init__.py
submitr/tests/conftest_settings.py
submitr/tests/data/f1_R1.fastq.gz
submitr/tests/data/f1_R2.fastq.gz
submitr/tests/data/f2_R1.fastq.gz
submitr/tests/data/f2_R2.fastq.gz
submitr/tests/data/ingestion_submission.json
submitr/tests/data/profiles.json
submitr/tests/data/simulated_bundle.json
submitr/tests/data/submission_simple.xlsx
submitr/tests/data/submission_simple2.xlsx
submitr/tests/data/submission_test.xlsx
submitr/tests/data/submission_test_with_errors.xlsx
submitr/tests/data/test1_R1.fastq.gz
submitr/tests/data/test1_R2.fastq.gz
submitr/tests/data/test_custom_column_mappings.xlsx
submitr/tests/integration/test_rclone_support.py
submitr/tests/integration/test_rclone_support_new.py
smaht_submitr-1.12.0.dist-info/LICENSE.txt
smaht_submitr-1.12.0.dist-info/METADATA
smaht_submitr-1.12.0.dist-info/WHEEL
smaht_submitr-1.12.0.dist-info/entry_points.txt
smaht_submitr-1.12.0.dist-info/RECORD
