Metadata-Version: 2.1
Name: smaht-submitr
Version: 1.12.0
Summary: Support for uploading file submissions to SMAHT.
Home-page: https://github.com/smaht-dac/submitr
License: MIT
Keywords: submitr,smaht
Author: SMaHT DAC
Author-email: smhelp@hms-dbmi.atlassian.net 
Requires-Python: >=3.8.1,<3.13
Classifier: Development Status :: 4 - Beta
Classifier: Intended Audience :: Developers
Classifier: Intended Audience :: Science/Research
Classifier: License :: OSI Approved :: MIT License
Classifier: Natural Language :: English
Classifier: Programming Language :: Python :: 3
Classifier: Programming Language :: Python :: 3.9
Classifier: Programming Language :: Python :: 3.10
Classifier: Programming Language :: Python :: 3.11
Classifier: Programming Language :: Python :: 3.12
Classifier: Programming Language :: Python :: 3.8
Classifier: Topic :: Database :: Database Engines/Servers
Requires-Dist: PyYAML (>=6.0.1,<7.0.0)
Requires-Dist: boto3 (>=1.36.5,<2.0.0)
Requires-Dist: dcicutils (>=8.18.3,<9.0.0)
Requires-Dist: google-cloud-storage (>=2.16.0,<3.0.0)
Requires-Dist: googleapi (>=0.1.0,<0.2.0)
Requires-Dist: pyinstaller (>=6.8.0,<7.0.0)
Requires-Dist: requests (>=2.31.0,<3.0.0)
Project-URL: Repository, https://github.com/smaht-dac/submitr.git
